ddcmakerVirtual/__init__.py
ddcmakerVirtual/baidu-aip.py
ddcmakerVirtual/car.py
ddcmakerVirtual/check_code_safe.py
ddcmakerVirtual/dog.py
ddcmakerVirtual/killprocess.py
ddcmakerVirtual/opcode.py
ddcmakerVirtual/robot.weights.py
ddcmakerVirtual/robotic_arm.py
ddcmakerVirtual/showlib.py
ddcmakerVirtual/spider.py
ddcmakerVirtual/voice.py
ddcmakerVirtual/whiterobot.py
ddcmakerVirtual-0.0.2.dist-info/LICENSE.txt
ddcmakerVirtual-0.0.2.dist-info/METADATA
ddcmakerVirtual-0.0.2.dist-info/WHEEL
ddcmakerVirtual-0.0.2.dist-info/top_level.txt
ddcmakerVirtual-0.0.2.dist-info/RECORD
